{
  "examples": {
    "": {
      "summary": "Default configuration",
      "description": "The defaults a new datasource starts with: no authentication, no TLS overrides, no trace-to-X mappings, trace-by-ID time parameters disabled. Only root.url needs to be filled in to get a working datasource pointed at a Jaeger query server on localhost:16686.",
      "value": {
        "jsonData": {},
        "secureJsonData": {
          "basicAuthPassword": ""
        },
        "url": "http://localhost:16686"
      }
    },
    "basicAuth": {
      "summary": "Basic authentication",
      "description": "Authenticate with a Jaeger that requires HTTP Basic. Both basicAuth and basicAuthUser live at the datasource root; only basicAuthPassword is secret. The SDK's HTTPClientOptions wires the credentials automatically (pkg/jaeger/jaeger.go:28).",
      "value": {
        "basicAuth": true,
        "basicAuthUser": "grafana",
        "jsonData": {},
        "secureJsonData": {
          "basicAuthPassword": "REPLACE_WITH_PASSWORD"
        },
        "url": "https://jaeger.example.com"
      }
    },
    "fullObservability": {
      "summary": "Full observability wiring (trace ↔ logs / metrics)",
      "description": "Jaeger wired to Loki (logs) and Prometheus (metrics). Uses the v2 tracesToLogs shape; nodeGraph and spanBar='Duration' are enabled. Note that Jaeger, unlike Tempo, has no trace-to-profiles or service-graph section in the editor.",
      "value": {
        "jsonData": {
          "nodeGraph": {
            "enabled": true
          },
          "spanBar": {
            "type": "Duration"
          },
          "tracesToLogsV2": {
            "customQuery": false,
            "datasourceUid": "loki",
            "filterBySpanID": false,
            "filterByTraceID": true,
            "spanEndTimeShift": "1m",
            "spanStartTimeShift": "-1m",
            "tags": [
              {
                "key": "service.name",
                "value": "service_name"
              },
              {
                "key": "cluster"
              }
            ]
          },
          "tracesToMetrics": {
            "datasourceUid": "prometheus",
            "queries": [
              {
                "name": "Error rate",
                "query": "sum(rate(traces_spanmetrics_calls_total{status_code=\"STATUS_CODE_ERROR\", $__tags}[$__rate_interval]))"
              },
              {
                "name": "P95 latency",
                "query": "histogram_quantile(0.95, sum(rate(traces_spanmetrics_latency_bucket{$__tags}[$__rate_interval])) by (le))"
              }
            ],
            "spanEndTimeShift": "2m",
            "spanStartTimeShift": "-2m",
            "tags": [
              {
                "key": "service.name",
                "value": "service"
              }
            ]
          }
        },
        "secureJsonData": {
          "basicAuthPassword": ""
        },
        "url": "https://jaeger.example.com"
      }
    },
    "legacyTracesToLogs": {
      "summary": "Legacy tracesToLogs (v1) — migrated on read",
      "description": "A datasource stored before the v2 shape landed. `getTraceToLogsOptions` transforms tracesToLogs → tracesToLogsV2 at editor load; the next save wipes tracesToLogs entirely. Kept as an example so provisioning tooling knows the shape is still round-trippable.",
      "value": {
        "jsonData": {
          "tracesToLogs": {
            "datasourceUid": "loki",
            "filterByTraceID": true,
            "mapTagNamesEnabled": false,
            "spanEndTimeShift": "1m",
            "spanStartTimeShift": "-1m",
            "tags": [
              "service.name",
              "cluster"
            ]
          }
        },
        "secureJsonData": {
          "basicAuthPassword": ""
        },
        "url": "https://jaeger.example.com"
      }
    },
    "noAuth": {
      "summary": "No authentication",
      "description": "A public or network-isolated Jaeger with no HTTP-level auth. Node graph is enabled for a richer trace view.",
      "value": {
        "jsonData": {
          "nodeGraph": {
            "enabled": true
          }
        },
        "secureJsonData": {
          "basicAuthPassword": ""
        },
        "url": "http://jaeger.example.com:16686"
      }
    },
    "oauthForward": {
      "summary": "Forward OAuth Identity",
      "description": "Forward the signed-in user's upstream OAuth identity to Jaeger. The editor writes only jsonData.oauthPassThru; there is no accompanying secret.",
      "value": {
        "jsonData": {
          "oauthPassThru": true
        },
        "secureJsonData": {
          "basicAuthPassword": ""
        },
        "url": "https://jaeger.example.com"
      }
    },
    "tlsMutualAuth": {
      "summary": "TLS mutual auth (mTLS)",
      "description": "Jaeger requiring mTLS. jsonData.tlsAuth=true triggers the SDK to build a client-authenticated transport using serverName plus the PEM-encoded client cert and key in secureJsonData.",
      "value": {
        "jsonData": {
          "serverName": "jaeger.example.com",
          "tlsAuth": true
        },
        "secureJsonData": {
          "tlsClientCert": "-----BEGIN CERTIFICATE-----\n...\n-----END CERTIFICATE-----",
          "tlsClientKey": "-----BEGIN RSA PRIVATE KEY-----\n...\n-----END RSA PRIVATE KEY-----"
        },
        "url": "https://jaeger.example.com"
      }
    },
    "tlsSelfSignedCA": {
      "summary": "Self-signed CA verification",
      "description": "Jaeger behind a private CA. jsonData.tlsAuthWithCACert=true tells the SDK to verify the server certificate against the PEM-encoded CA in secureJsonData.tlsCACert.",
      "value": {
        "jsonData": {
          "tlsAuthWithCACert": true
        },
        "secureJsonData": {
          "tlsCACert": "-----BEGIN CERTIFICATE-----\n...\n-----END CERTIFICATE-----"
        },
        "url": "https://jaeger.internal.corp"
      }
    },
    "traceIdTimeParams": {
      "summary": "Query trace by ID with time parameters",
      "description": "Enable the plugin-local traceIdTimeParams toggle so the backend appends start / end query parameters to GET /api/traces/{traceID}. Useful when Jaeger's storage backend requires a time hint to locate long-retained traces (pkg/jaeger/client.go:242-266).",
      "value": {
        "jsonData": {
          "traceIdTimeParams": {
            "enabled": true
          }
        },
        "secureJsonData": {
          "basicAuthPassword": ""
        },
        "url": "https://jaeger.example.com"
      }
    }
  }
}
